{
  "available": true,
  "selected_model": "hist_gradient_boosting",
  "selection_metric": "spatial_holdout_average_precision_then_cross_validated_average_precision",
  "rows": 5173,
  "positive_labels": 327,
  "negative_labels": 4846,
  "training_points": 128,
  "feature_count": 28,
  "random_holdout_average_precision": 0.719170715981121,
  "random_holdout_roc_auc": 0.9264167270385575,
  "spatial_holdout_average_precision": 0.5633832816157106,
  "spatial_holdout_roc_auc": 0.8588021754885381,
  "spatial_holdout_top10_precision": 1.0,
  "point_qc": {
    "rows": 176,
    "matched_existing_candidates": 128,
    "outside_analysis_extent": 48,
    "analysis_flags": {
      "matched_existing_candidate": 128,
      "outside_current_analysis_extent": 48
    }
  },
  "source_files": [
    {
      "path": "reports/actual_ulster_field_report_metrics.json",
      "exists": true,
      "bytes": 11444
    },
    {
      "path": "reports/extracted_points_analysis.json",
      "exists": true,
      "bytes": 5997
    },
    {
      "path": "data/processed/high_confidence_training_points.csv",
      "exists": true,
      "bytes": 24214
    }
  ]
}